mcp_copilotcli_history/__init__.py
mcp_copilotcli_history/__main__.py
mcp_copilotcli_history/py.typed
mcp_copilotcli_history/server.py
mcp_copilotcli_history-0.1.1.dist-info/METADATA
mcp_copilotcli_history-0.1.1.dist-info/WHEEL
mcp_copilotcli_history-0.1.1.dist-info/entry_points.txt
mcp_copilotcli_history-0.1.1.dist-info/licenses/LICENSE
mcp_copilotcli_history-0.1.1.dist-info/RECORD
