Metadata-Version: 2.4
Name: mcp-copilotcli-history
Version: 0.1.1
Summary: MCP server for searching GitHub Copilot conversation history
Project-URL: Homepage, https://github.com/MicroMichaelIE/mcp-copilotcli-history
Project-URL: Repository, https://github.com/MicroMichaelIE/mcp-copilotcli-history
Project-URL: Changelog, https://github.com/MicroMichaelIE/mcp-copilotcli-history/blob/main/CHANGELOG.md
Project-URL: Issues, https://github.com/MicroMichaelIE/mcp-copilotcli-history/issues
Author: Michael Lawlor
License: MIT
License-File: LICENSE
Keywords: ai,copilot,history,mcp,model-context-protocol,search
Classifier: Development Status :: 4 - Beta
Classifier: Intended Audience :: Developers
Classifier: License :: OSI Approved :: MIT License
Classifier: Programming Language :: Python :: 3
Classifier: Programming Language :: Python :: 3.13
Classifier: Topic :: Software Development :: Libraries :: Python Modules
Classifier: Typing :: Typed
Requires-Python: >=3.13
Requires-Dist: mcp>=1.0.0
Provides-Extra: dev
Requires-Dist: build>=1.0.0; extra == 'dev'
Requires-Dist: pyright>=1.1.0; extra == 'dev'
Requires-Dist: ruff>=0.8.0; extra == 'dev'
